formsnake/__init__.py
formsnake/__main__.py
formsnake/alembic.ini
formsnake/config.py
formsnake/exc.py
formsnake/models.py
formsnake/server.py
formsnake/utils.py
formsnake/alembic/README
formsnake/alembic/env.py
formsnake/alembic/script.py.mako
formsnake/alembic/versions/fe45dd0d3fc1_initial_db_structure.py
formsnake_api-0.0.2.dist-info/LICENSE
formsnake_api-0.0.2.dist-info/METADATA
formsnake_api-0.0.2.dist-info/WHEEL
formsnake_api-0.0.2.dist-info/entry_points.txt
formsnake_api-0.0.2.dist-info/top_level.txt
formsnake_api-0.0.2.dist-info/RECORD
