Metadata-Version: 2.1
Name: formsnake-api
Version: 0.0.2
Summary: Open Source alternative to Google Forms.
Home-page: https://github.com/formsnake/formsnake-api
Author: Dakota Brown
Author-email: dakota.kae.brown@gmail.com
License: MIT
Platform: UNKNOWN
Classifier: License :: OSI Approved :: MIT License
Classifier: Programming Language :: Python :: 3.8
Requires-Dist: flask (>=2)
Requires-Dist: flask-sqlalchemy
Requires-Dist: flask-marshmallow
Requires-Dist: flask-mail
Requires-Dist: marshmallow-sqlalchemy
Requires-Dist: psycopg2
Requires-Dist: cx-oracle
Requires-Dist: pymssql
Requires-Dist: pycryptodome
Requires-Dist: alembic
Requires-Dist: pymysql
Requires-Dist: python-dotenv
Requires-Dist: flask-bcrypt
Requires-Dist: beautifulsoup4
Requires-Dist: uwsgi
Requires-Dist: flask-cors
Requires-Dist: PyJWT
